attribution_quality/__init__.py
attribution_quality/base.py
attribution_quality/gradcam.py
attribution_quality/hooks.py
attribution_quality/ignore__seggradcam.py
attribution_quality/kernel_weighted.py
attribution_quality/metrics.py
attribution_quality/nnunet_utils.py
attribution_quality/optional_imports.py
attribution_quality/scorecam.py
attribution_quality/utils.py
attribution_quality/splitnet/__init__.py
attribution_quality/splitnet/split_nnunet.py
attribution_quality/splitnet/splitnet.py
attribution_quality-1.0.dist-info/LICENSE.txt
attribution_quality-1.0.dist-info/METADATA
attribution_quality-1.0.dist-info/WHEEL
attribution_quality-1.0.dist-info/top_level.txt
attribution_quality-1.0.dist-info/RECORD
