Metadata-Version: 2.1
Name: attribution-quality
Version: 1.0
Summary: KernelWeighted Contribution implementation for visual understanding of deep learning segmentation
Home-page: https://github.com/Mullans/AttributionQuality
Author: Sean Mullan
Author-email: Sean Mullan <sean-mullan@uiowa.edu>
License: MIT
Project-URL: Source, https://github.com/Mullans/AttributionQuality
Platform: any
Classifier: License :: OSI Approved :: MIT License
Classifier: Intended Audience :: Science/Research
Classifier: Operating System :: OS Independent
Classifier: Programming Language :: Python
Classifier: Topic :: Scientific/Engineering
Classifier: Topic :: Scientific/Engineering :: Information Analysis
Requires-Python: >=3.9
License-File: LICENSE.txt
Requires-Dist: numpy
Requires-Dist: scikit-image
Requires-Dist: torch
Requires-Dist: tqdm
